pyglsl/__init__.py
pyglsl/glsl.py
pyglsl/interface.py
pyglsl/parse.py
pyglsl/shaderdef.py
pyglsl/stage.py
pyglsl/types.py
pyglsl-0.0.8.dist-info/licenses/LICENSE
pyglsl-0.0.8.dist-info/METADATA
pyglsl-0.0.8.dist-info/WHEEL
pyglsl-0.0.8.dist-info/top_level.txt
pyglsl-0.0.8.dist-info/RECORD
