Metadata-Version: 2.4
Name: pyglsl
Version: 0.0.8
Summary: Transform Python to GLSL
Home-page: https://github.com/takeiteasy/pyglsl
Author: George Watson
Author-email: George Watson <gigolo@hotmail.co.uk>
Project-URL: Homepage, https://github.com/takeiteasy/pyglsl
Project-URL: Issues, https://github.com/takeiteasy/pyglsl/issues
Classifier: Programming Language :: Python :: 3
Classifier: License :: OSI Approved :: MIT License
Classifier: Operating System :: OS Independent
Requires-Python: >=3.10
License-File: LICENSE
Requires-Dist: attrs==25.1.0
Requires-Dist: typing==3.7.4.3
Dynamic: author
Dynamic: home-page
Dynamic: license-file
